fastq_handler/__init__.py
fastq_handler/__main__.py
fastq_handler/actions.py
fastq_handler/configs.py
fastq_handler/fastq_handler.py
fastq_handler/records.py
fastq_handler/utilities.py
fastq_handler-0.2.0.dist-info/entry_points.txt
fastq_handler-0.2.0.dist-info/LICENSE
fastq_handler-0.2.0.dist-info/WHEEL
fastq_handler-0.2.0.dist-info/METADATA
fastq_handler-0.2.0.dist-info/RECORD
